receptor/__init__.py
receptor/__main__.py
receptor/config.py
receptor/controller.py
receptor/entrypoints.py
receptor/exceptions.py
receptor/receptor.py
receptor/router.py
receptor/stats.py
receptor/work.py
receptor/buffers/__init__.py
receptor/buffers/base.py
receptor/buffers/file.py
receptor/connection/__init__.py
receptor/connection/base.py
receptor/connection/manager.py
receptor/connection/sock.py
receptor/connection/ws.py
receptor/messages/__init__.py
receptor/messages/directive.py
receptor/messages/envelope.py
receptor/security/__init__.py
receptor/worker/__init__.py
receptor/worker/demo.py
test/__init__.py
test/perf/__init__.py
test/perf/test_ping.py
test/perf/test_route.py
test/perf/test_websockets.py
test/unit/__init__.py
test/unit/test_durable_buffer.py
test/unit/test_framedbuffer.py
test/unit/test_message.py
test/unit/test_router.py
receptor-0.6.4.dist-info/LICENSE.md
receptor-0.6.4.dist-info/METADATA
receptor-0.6.4.dist-info/WHEEL
receptor-0.6.4.dist-info/entry_points.txt
receptor-0.6.4.dist-info/top_level.txt
receptor-0.6.4.dist-info/RECORD
