Metadata-Version: 2.1
Name: receptor
Version: 0.6.4
Summary: UNKNOWN
Home-page: https://github.com/project-receptor/receptor
Author: Red Hat
License: Apache
Platform: UNKNOWN
Classifier: Programming Language :: Python :: 3
Requires-Python: >=3.6
License-File: LICENSE.md
Requires-Dist: prometheus-client (<0.9,>=0.7.1)
Requires-Dist: aiohttp (<4.0,>=3.6.2)
Requires-Dist: python-dateutil (>=2.8.1)
